MANIFEST.in
README.rst
setup.cfg
setup.py
fui/__init__.py
fui.memberlist.egg-info/PKG-INFO
fui.memberlist.egg-info/SOURCES.txt
fui.memberlist.egg-info/dependency_links.txt
fui.memberlist.egg-info/entry_points.txt
fui.memberlist.egg-info/namespace_packages.txt
fui.memberlist.egg-info/not-zip-safe
fui.memberlist.egg-info/paster_plugins.txt
fui.memberlist.egg-info/requires.txt
fui.memberlist.egg-info/top_level.txt
fui/memberlist/__init__.py
fui/memberlist/config.py
fui/memberlist/configure.zcml
fui/memberlist/interfaces.py
fui/memberlist/browser/__init__.py
fui/memberlist/browser/configure.zcml
fui/memberlist/browser/homepage.png
fui/memberlist/browser/mail.png
fui/memberlist/browser/memberlist.png
fui/memberlist/browser/memberlist.pt
fui/memberlist/browser/memberlist.py
fui/memberlist/browser/style.css
fui/memberlist/content/__init__.py
fui/memberlist/content/configure.zcml
fui/memberlist/content/memberlist.py
fui/memberlist/profiles/default/catalog.xml
fui/memberlist/profiles/default/cssregistry.xml
fui/memberlist/profiles/default/factorytool.xml
fui/memberlist/profiles/default/rolemap.xml
fui/memberlist/profiles/default/types.xml
fui/memberlist/profiles/default/types/MemberList.xml
fui/memberlist/tests/__init__.py
fui/memberlist/tests/base.py
fui/memberlist/tests/test_doctest.py