Metadata-Version: 1.0
Name: fui.memberlist
Version: 0.3.1
Summary: UNKNOWN
Home-page: http://github.com/espenak/fui.memberlist
Author: Espen A. Kristiansen
Author-email: post@espenak.net
License: GPL
Platform: UNKNOWN
Classifier: Framework :: Plone
Classifier: Programming Language :: Python
Classifier: Topic :: Software Development :: Libraries :: Python Modules
